{"otherData": {},"traceEvents":[{"cat":"function","dur":96,"name":"void __cdecl QCat::Renderer2D::Shutdown(void)","ph":"X","pid":0,"tid":1462593905,"ts":167607780117},{"cat":"function","dur":169,"name":"__cdecl QCat::Application::~Application(void)","ph":"X","pid":0,"tid":1462593905,"ts":167607780115},{"cat":"function","dur":1303,"name":"void __cdecl QCat::ImGuiLayer::OnDetach(void)","ph":"X","pid":0,"tid":1462593905,"ts":167607780330},{"cat":"function","dur":27,"name":"__cdecl QCat::WindowsWindow::~WindowsWindow(void)","ph":"X","pid":0,"tid":1462593905,"ts":167607781737}]}